btfxwss/__init__.py
btfxwss/client.py
btfxwss/connection.py
btfxwss/queue_processor.py
btfxwss2-1.2.1.dist-info/LICENSE.txt
btfxwss2-1.2.1.dist-info/METADATA
btfxwss2-1.2.1.dist-info/WHEEL
btfxwss2-1.2.1.dist-info/top_level.txt
btfxwss2-1.2.1.dist-info/RECORD
