Metadata-Version: 2.1
Name: btfxwss2
Version: 1.2.1
Summary: Python 3.5+ Websocket Client for the Bitfinex WSS API.
Home-page: https://github.com/xmurobi/btfxwss
Author: Nils Diefenbach
Author-email: 23okrs20+pypi@mykolab.com
License: LICENCSE
Platform: UNKNOWN
Requires-Dist: websocket-client
